README.txt
setup.py
Products/__init__.py
Products.CacheSetup.egg-info/PKG-INFO
Products.CacheSetup.egg-info/SOURCES.txt
Products.CacheSetup.egg-info/dependency_links.txt
Products.CacheSetup.egg-info/entry_points.txt
Products.CacheSetup.egg-info/namespace_packages.txt
Products.CacheSetup.egg-info/not-zip-safe
Products.CacheSetup.egg-info/requires.txt
Products.CacheSetup.egg-info/top_level.txt
Products/CacheSetup/VERSION.txt
Products/CacheSetup/__init__.py
Products/CacheSetup/cachesetup_tool_icon.gif
Products/CacheSetup/cachingPoliciesDummy.dtml
Products/CacheSetup/cmf_utils.py
Products/CacheSetup/config.py
Products/CacheSetup/configure.zcml
Products/CacheSetup/enabler.py
Products/CacheSetup/interfaces.py
Products/CacheSetup/patch.py
Products/CacheSetup/patch_cmf.py
Products/CacheSetup/patch_five.py
Products/CacheSetup/patch_utils.py
Products/CacheSetup/permissions.py
Products/CacheSetup/setuphandlers.py
Products/CacheSetup/utils.py
Products/CacheSetup/vocabulary.py
Products/CacheSetup/Extensions/Install.py
Products/CacheSetup/Extensions/__init__.py
Products/CacheSetup/Extensions/policy_1.py
Products/CacheSetup/Extensions/policy_2.py
Products/CacheSetup/Extensions/policy_utils.py
Products/CacheSetup/Extensions/utils.py
Products/CacheSetup/content/__init__.py
Products/CacheSetup/content/base_cache_rule.py
Products/CacheSetup/content/cache_tool.py
Products/CacheSetup/content/caching_policy_manager.py
Products/CacheSetup/content/content_cache_rule.py
Products/CacheSetup/content/header_set.py
Products/CacheSetup/content/header_set_folder.py
Products/CacheSetup/content/interfaces.py
Products/CacheSetup/content/nocatalog.py
Products/CacheSetup/content/phcm_cache_rule.py
Products/CacheSetup/content/policy_folder.py
Products/CacheSetup/content/rule_folder.py
Products/CacheSetup/content/template_cache_rule.py
Products/CacheSetup/exportimport/__init__.py
Products/CacheSetup/exportimport/atcontent.py
Products/CacheSetup/exportimport/cachefu.py
Products/CacheSetup/exportimport/configure.zcml
Products/CacheSetup/profiles/default/actionicons.xml
Products/CacheSetup/profiles/default/cachesettings.xml
Products/CacheSetup/profiles/default/cachesetup-various.txt
Products/CacheSetup/profiles/default/controlpanel.xml
Products/CacheSetup/profiles/default/export_steps.xml
Products/CacheSetup/profiles/default/factorytool.xml
