Metadata-Version: 1.0
Name: Products.CacheSetup
Version: 1.2.1
Summary: Control caching of Plone sites
Home-page: http://svn.plone.org/svn/collective/Products.CacheSetup
Author: Geoff Davis
Author-email: plone-developers@lists.sourceforge.net
License: ZPL
Keywords: cache caching
Platform: UNKNOWN
Classifier: Framework :: Plone
Classifier: Programming Language :: Python
Classifier: Topic :: Software Development :: Libraries :: Python Modules
